aiotrade/__init__.py
aiotrade/_errors.py
aiotrade/_http.py
aiotrade/_protocols.py
aiotrade/_session.py
aiotrade/_types.py
aiotrade/caches/__init__.py
aiotrade/caches/_base.py
aiotrade/caches/bingx.py
aiotrade/caches/bybit.py
aiotrade/clients/__init__.py
aiotrade/clients/bingx/__init__.py
aiotrade/clients/bingx/_http.py
aiotrade/clients/bingx/_mixins/__init__.py
aiotrade/clients/bingx/_mixins/_account/__init__.py
aiotrade/clients/bingx/_mixins/_account/_fund.py
aiotrade/clients/bingx/_mixins/_account/_sub.py
aiotrade/clients/bingx/_mixins/_account/_wallet.py
aiotrade/clients/bingx/_mixins/_common.py
aiotrade/clients/bingx/_mixins/_mfutures/__init__.py
aiotrade/clients/bingx/_mixins/_mfutures/_market.py
aiotrade/clients/bingx/_mixins/_mfutures/_trade.py
aiotrade/clients/bingx/_mixins/_spot/__init__.py
aiotrade/clients/bingx/_mixins/_spot/_account.py
aiotrade/clients/bingx/_mixins/_spot/_market.py
aiotrade/clients/bingx/_mixins/_spot/_trade.py
aiotrade/clients/bingx/_mixins/_spot/_wallet.py
aiotrade/clients/bingx/_mixins/_swap/__init__.py
aiotrade/clients/bingx/_mixins/_swap/_account.py
aiotrade/clients/bingx/_mixins/_swap/_market.py
aiotrade/clients/bingx/_mixins/_swap/_trade.py
aiotrade/clients/bybit/__init__.py
aiotrade/clients/bybit/_http.py
aiotrade/clients/bybit/_mixins/__init__.py
aiotrade/clients/bybit/_mixins/_account.py
aiotrade/clients/bybit/_mixins/_market.py
aiotrade/clients/bybit/_mixins/_position.py
aiotrade/clients/bybit/_mixins/_trade.py
aiotrade/py.typed
aiotrade/types/__init__.py
aiotrade/types/bingx.py
aiotrade/types/bybit.py
aiotrade_sdk-0.2.0.dist-info/METADATA
aiotrade_sdk-0.2.0.dist-info/WHEEL
aiotrade_sdk-0.2.0.dist-info/licenses/LICENSE
aiotrade_sdk-0.2.0.dist-info/RECORD
