Metadata-Version: 2.4
Name: aiotrade-sdk
Version: 0.2.0
Summary: High-performance async trading API client for Python supporting BingX and Bybit exchanges with intelligent session and cache management
License-Expression: MIT
License-File: LICENSE
Keywords: trading,api,async,cryptocurrency,exchange,bingx,bybit,finance,asyncio,aiohttp
Author: Daniil Pavlovich
Author-email: layred.dota2@mail.ru
Requires-Python: >=3.12,<3.15
Classifier: Programming Language :: Python :: 3
Classifier: Programming Language :: Python :: 3.12
Classifier: Programming Language :: Python :: 3.13
Classifier: Programming Language :: Python :: 3.14
Requires-Dist: aiohttp (>=3.13.3,<4.0.0)
Requires-Dist: orjson (>=3.11.5,<4.0.0)
Project-URL: Changelog, https://github.com/vispar-tech/aiotrade/blob/main/CHANGELOG.md
Project-URL: Documentation, https://github.com/vispar-tech/aiotrade#readme
Project-URL: Homepage, https://github.com/vispar-tech/aiotrade
Project-URL: Issues, https://github.com/vispar-tech/aiotrade/issues
Project-URL: Repository, https://github.com/vispar-tech/aiotrade
